{
  "lesson": "08-cnns-rnns-for-text",
  "title": "CNNs and RNNs for Text",
  "questions": [
    {
      "stage": "pre",
      "question": "对词嵌入应用宽度为 3 的一维卷积过滤器实际上在学习什么？",
      "options": [
        "可学习的二元组检测器",
        "位置嵌入",
        "可学习的三元组（n-gram）检测器",
        "一元组计数"
      ],
      "correct": 2,
      "explanation": "宽度为 3 的过滤器跨越三个连续 token，充当可学习的三元组检测器。"
    },
    {
      "stage": "pre",
      "question": "为什么 LSTM 使用以加法交互为主的细胞状态？",
      "options": [
        "加法流让梯度可以在长序列中传播而不消失或爆炸",
        "更快的 softmax",
        "节省内存",
        "避免矩阵求逆"
      ],
      "correct": 0,
      "explanation": "细胞状态的高速公路使梯度在数百步中保持稳定，解决了梯度消失问题。"
    },
    {
      "stage": "check",
      "question": "为什么 TextCNN 在卷积层之后使用全局最大池化？",
      "options": [
        "启用反向传播",
        "移除嵌入",
        "缩减词汇表",
        "最大池化通过选择每个过滤器的最强激活，给出固定大小、位置不变的表示"
      ],
      "correct": 3,
      "explanation": "全局最大池化产生固定大小的特征向量，与输入长度无关，且具有位置不变性。"
    },
    {
      "stage": "check",
      "question": "双向 RNN 相比单向 RNN 在序列标注上的主要优势是什么？",
      "options": [
        "训练更快",
        "每个 token 的表示都能看到左右两侧的上下文，这对标注至关重要",
        "避免嵌入",
        "内存更便宜"
      ],
      "correct": 1,
      "explanation": "双向网络拼接正向和反向隐藏状态，使标签可以使用完整的上下文。"
    },
    {
      "stage": "check",
      "question": "为什么对 LSTM 输出进行最大池化通常优于仅使用最后一个隐藏状态进行分类？",
      "options": [
        "最大池化可以反向传播；最后状态不行",
        "长序列末尾的信息往往主导最后状态，隐藏了早期的证据",
        "最大池化去除了大小写",
        "最后状态池化忽略填充"
      ],
      "correct": 1,
      "explanation": "最大池化聚合跨位置的最强信号；最后状态可能丢失早期的证据。"
    },
    {
      "stage": "post",
      "question": "LSTM/RNN 编码器-解码器的哪个局限性促使了注意力机制的出现？",
      "options": [
        "需要子词分词器",
        "无法使用嵌入",
        "解码器只看到固定大小的编码器状态，在长输入上丢失细节；循环还使训练串行化",
        "无法嵌入 token"
      ],
      "correct": 2,
      "explanation": "固定大小的摘要加上串行训练是注意力机制消除的两个失败。"
    },
    {
      "stage": "post",
      "question": "2026 年什么情况下 TextCNN 或 BiLSTM 仍然优于 Transformer？",
      "options": [
        "图像输入时",
        "边缘/设备端、流式逐 token 输入，或小数据量基线",
        "数据集是多语言时",
        "延迟要求极宽松时"
      ],
      "correct": 1,
      "explanation": "小架构在边缘推理、流式输入和快速基线上仍然胜出。"
    },
    {
      "stage": "post",
      "question": "普通 RNN 中的梯度消失问题是什么？",
      "options": [
        "反复乘以小于 1 的循环权重使早期步骤的梯度趋于零",
        "嵌入矩阵变成奇异矩阵",
        "输入变为零",
        "损失变为负数"
      ],
      "correct": 0,
      "explanation": "没有门控时，长乘积梯度消失（或爆炸）；这就是 LSTM 和 GRU 存在的原因。"
    }
  ]
}
